apimaticcalculatorpythonv6_demo/__init__.py
apimaticcalculatorpythonv6_demo/api_helper.py
apimaticcalculatorpythonv6_demo/apimaticcalculatorpythonv6_demo_client.py
apimaticcalculatorpythonv6_demo/configuration.py
apimaticcalculatorpythonv6_demo/decorators.py
apimaticcalculatorpythonv6_demo/controllers/__init__.py
apimaticcalculatorpythonv6_demo/controllers/base_controller.py
apimaticcalculatorpythonv6_demo/controllers/calculator_dev_ops_conf.py
apimaticcalculatorpythonv6_demo/exceptions/__init__.py
apimaticcalculatorpythonv6_demo/exceptions/api_exception.py
apimaticcalculatorpythonv6_demo/http/__init__.py
apimaticcalculatorpythonv6_demo/http/http_call_back.py
apimaticcalculatorpythonv6_demo/http/http_client.py
apimaticcalculatorpythonv6_demo/http/http_context.py
apimaticcalculatorpythonv6_demo/http/http_method_enum.py
apimaticcalculatorpythonv6_demo/http/http_request.py
apimaticcalculatorpythonv6_demo/http/http_response.py
apimaticcalculatorpythonv6_demo/http/requests_client.py
apimaticcalculatorpythonv6_demo/models/__init__.py
apimaticcalculatorpythonv6_demo/models/operation_type.py
tests/__init__.py
tests/http_response_catcher.py
tests/test_helper.py
tests/controllers/__init__.py
tests/controllers/controller_test_base.py
tests/controllers/test_calculator_dev_ops_conf.py
apimaticcalculatorpythonv6Demo-1.0.2.dist-info/LICENSE
apimaticcalculatorpythonv6Demo-1.0.2.dist-info/METADATA
apimaticcalculatorpythonv6Demo-1.0.2.dist-info/WHEEL
apimaticcalculatorpythonv6Demo-1.0.2.dist-info/top_level.txt
apimaticcalculatorpythonv6Demo-1.0.2.dist-info/RECORD
